odoo/addons/purchase_deposit_analytic/README.rst
odoo/addons/purchase_deposit_analytic/__init__.py
odoo/addons/purchase_deposit_analytic/__manifest__.py
odoo/addons/purchase_deposit_analytic/i18n/purchase_deposit_analytic.pot
odoo/addons/purchase_deposit_analytic/readme/CONTRIBUTORS.rst
odoo/addons/purchase_deposit_analytic/readme/DESCRIPTION.rst
odoo/addons/purchase_deposit_analytic/static/description/icon.png
odoo/addons/purchase_deposit_analytic/static/description/index.html
odoo/addons/purchase_deposit_analytic/tests/__init__.py
odoo/addons/purchase_deposit_analytic/tests/test_purchase_deposit_analytic.py
odoo/addons/purchase_deposit_analytic/wizard/__init__.py
odoo/addons/purchase_deposit_analytic/wizard/purchase_make_invoice_advance.py
odoo/addons/purchase_deposit_analytic/wizard/purchase_make_invoice_advance_views.xml
odoo_addon_purchase_deposit_analytic-15.0.1.0.0.2.dist-info/METADATA
odoo_addon_purchase_deposit_analytic-15.0.1.0.0.2.dist-info/WHEEL
odoo_addon_purchase_deposit_analytic-15.0.1.0.0.2.dist-info/top_level.txt
odoo_addon_purchase_deposit_analytic-15.0.1.0.0.2.dist-info/RECORD
